<?xml version="1.0" encoding="UTF-8"?><record_update table="sys_ux_client_script">
    <sys_ux_client_script action="DELETE">
        <controller_preset/>
        <includes/>
        <macroponent display_value="Interceptor default copy">4571cbcc47d63110036bbce5536d4326</macroponent>
        <name>Set category and orderType on select</name>
        <preset/>
        <required_translations>[
    
]</required_translations>
        <script><![CDATA[/**
* @param {params} params
* @param {api} params.api
* @param {any} params.event
* @param {any} params.imports
* @param {ApiHelpers} params.helpers
*/
function handler({
    api,
    event,
    helpers,
    imports
}) {
    switch (event.elementId) {
        case "new_product_card":
            if (api.state.category == "product" && api.state.orderType == "add") {
                api.setState("category", "");
                api.setState("orderType", "");
            } else {
                api.setState("category", "product");
                api.setState("orderType", "add");
            }
            break;
        case "new_service_card":
            if (api.state.category == "service" && api.state.orderType == "add") {
                api.setState("category", "");
                api.setState("orderType", "");
            } else {
                api.setState("category", "service");
                api.setState("orderType", "add");
            }
            break;
        case "change_product_card":
            if (api.state.category == "product" && api.state.orderType == "change") {
                api.setState("category", "");
                api.setState("orderType", "");
            } else {
                api.setState("category", "product");
                api.setState("orderType", "change");
            }
            break;
        case "change_service_card":
            if (api.state.category == "service" && api.state.orderType == "change") {
                api.setState("category", "");
                api.setState("orderType", "");
            } else {
                api.setState("category", "service");
                api.setState("orderType", "change");
            }
            break;
        case "cancel_product_card":
            if (api.state.category == "product" && api.state.orderType == "disconnect") {
                api.setState("category", "");
                api.setState("orderType", "");
            } else {
                api.setState("category", "product");
                api.setState("orderType", "disconnect");
            }
            break;
        case "disconnect_service_card":
            if (api.state.category == "service" && api.state.orderType == "disconnect") {
                api.setState("category", "");
                api.setState("orderType", "");
            } else {
                api.setState("category", "service");
                api.setState("orderType", "disconnect");
            }
            break;
        case "add_order_service_card":
            if (api.state.category == "service" && api.state.orderType == "add") {
                api.setState("category", "");
                api.setState("orderType", "");
            } else {
                api.setState("category", "service");
                api.setState("orderType", "add");
            }
            break;
        case "change_order_service_card":
            if (api.state.category == "service" && api.state.orderType == "change") {
                api.setState("category", "");
                api.setState("orderType", "");
            } else {
                api.setState("category", "service");
                api.setState("orderType", "change");
            }
            break;
        case "disconnect_order_service_card":
            if (api.state.category == "service" && api.state.orderType == "disconnect") {
                api.setState("category", "");
                api.setState("orderType", "");
            } else {
                api.setState("category", "service");
                api.setState("orderType", "disconnect");
            }
            break;
    }
}]]></script>
        <script_api_version>2.0.0</script_api_version>
        <sys_class_name>sys_ux_client_script</sys_class_name>
        <sys_created_by>admin</sys_created_by>
        <sys_created_on>2023-10-30 18:43:02</sys_created_on>
        <sys_id>d17183c0471a3110036bbce5536d43f7</sys_id>
        <sys_mod_count>1</sys_mod_count>
        <sys_name>Set category and orderType on select</sys_name>
        <sys_package display_value="AT&amp;amp;T Workspace" source="x_876519_att_work">e90c1d2e47c63110036bbce5536d43e6</sys_package>
        <sys_policy/>
        <sys_scope display_value="AT&amp;amp;T Workspace">e90c1d2e47c63110036bbce5536d43e6</sys_scope>
        <sys_update_name>sys_ux_client_script_d17183c0471a3110036bbce5536d43f7</sys_update_name>
        <sys_updated_by>admin</sys_updated_by>
        <sys_updated_on>2023-10-30 18:43:02</sys_updated_on>
        <target>macroponent</target>
        <type>default</type>
    </sys_ux_client_script>
    <sys_update_version action="INSERT_OR_UPDATE">
        <action>DELETE</action>
        <application display_value="AT&amp;amp;T Workspace">e90c1d2e47c63110036bbce5536d43e6</application>
        <file_path/>
        <instance_id>c90493d81be364d032182f8dee4bcbce</instance_id>
        <instance_name>dev111524</instance_name>
        <name>sys_ux_client_script_d17183c0471a3110036bbce5536d43f7</name>
        <payload>&lt;?xml version="1.0" encoding="UTF-8"?&gt;&lt;record_update table="sys_ux_client_script"&gt;&lt;sys_ux_client_script action="INSERT_OR_UPDATE"&gt;&lt;controller_preset/&gt;&lt;includes/&gt;&lt;macroponent display_value="Interceptor default copy"&gt;4571cbcc47d63110036bbce5536d4326&lt;/macroponent&gt;&lt;name&gt;Set category and orderType on select&lt;/name&gt;&lt;preset/&gt;&lt;required_translations&gt;[
    
]&lt;/required_translations&gt;&lt;script&gt;&lt;![CDATA[/**
* @param {params} params
* @param {api} params.api
* @param {any} params.event
* @param {any} params.imports
* @param {ApiHelpers} params.helpers
*/
function handler({
    api,
    event,
    helpers,
    imports
}) {
    switch (event.elementId) {
        case "new_product_card":
            if (api.state.category == "product" &amp;&amp; api.state.orderType == "add") {
                api.setState("category", "");
                api.setState("orderType", "");
            } else {
                api.setState("category", "product");
                api.setState("orderType", "add");
            }
            break;
        case "new_service_card":
            if (api.state.category == "service" &amp;&amp; api.state.orderType == "add") {
                api.setState("category", "");
                api.setState("orderType", "");
            } else {
                api.setState("category", "service");
                api.setState("orderType", "add");
            }
            break;
        case "change_product_card":
            if (api.state.category == "product" &amp;&amp; api.state.orderType == "change") {
                api.setState("category", "");
                api.setState("orderType", "");
            } else {
                api.setState("category", "product");
                api.setState("orderType", "change");
            }
            break;
        case "change_service_card":
            if (api.state.category == "service" &amp;&amp; api.state.orderType == "change") {
                api.setState("category", "");
                api.setState("orderType", "");
            } else {
                api.setState("category", "service");
                api.setState("orderType", "change");
            }
            break;
        case "cancel_product_card":
            if (api.state.category == "product" &amp;&amp; api.state.orderType == "disconnect") {
                api.setState("category", "");
                api.setState("orderType", "");
            } else {
                api.setState("category", "product");
                api.setState("orderType", "disconnect");
            }
            break;
        case "disconnect_service_card":
            if (api.state.category == "service" &amp;&amp; api.state.orderType == "disconnect") {
                api.setState("category", "");
                api.setState("orderType", "");
            } else {
                api.setState("category", "service");
                api.setState("orderType", "disconnect");
            }
            break;
        case "add_order_service_card":
            if (api.state.category == "service" &amp;&amp; api.state.orderType == "add") {
                api.setState("category", "");
                api.setState("orderType", "");
            } else {
                api.setState("category", "service");
                api.setState("orderType", "add");
            }
            break;
        case "change_order_service_card":
            if (api.state.category == "service" &amp;&amp; api.state.orderType == "change") {
                api.setState("category", "");
                api.setState("orderType", "");
            } else {
                api.setState("category", "service");
                api.setState("orderType", "change");
            }
            break;
        case "disconnect_order_service_card":
            if (api.state.category == "service" &amp;&amp; api.state.orderType == "disconnect") {
                api.setState("category", "");
                api.setState("orderType", "");
            } else {
                api.setState("category", "service");
                api.setState("orderType", "disconnect");
            }
            break;
    }
}]]&gt;&lt;/script&gt;&lt;script_api_version&gt;2.0.0&lt;/script_api_version&gt;&lt;sys_class_name&gt;sys_ux_client_script&lt;/sys_class_name&gt;&lt;sys_created_by&gt;admin&lt;/sys_created_by&gt;&lt;sys_created_on&gt;2023-10-30 18:43:02&lt;/sys_created_on&gt;&lt;sys_id&gt;d17183c0471a3110036bbce5536d43f7&lt;/sys_id&gt;&lt;sys_mod_count&gt;1&lt;/sys_mod_count&gt;&lt;sys_name&gt;Set category and orderType on select&lt;/sys_name&gt;&lt;sys_package display_value="AT&amp;amp;amp;T Workspace" source="x_876519_att_work"&gt;e90c1d2e47c63110036bbce5536d43e6&lt;/sys_package&gt;&lt;sys_policy/&gt;&lt;sys_scope display_value="AT&amp;amp;amp;T Workspace"&gt;e90c1d2e47c63110036bbce5536d43e6&lt;/sys_scope&gt;&lt;sys_update_name&gt;sys_ux_client_script_d17183c0471a3110036bbce5536d43f7&lt;/sys_update_name&gt;&lt;sys_updated_by&gt;admin&lt;/sys_updated_by&gt;&lt;sys_updated_on&gt;2023-10-30 18:43:02&lt;/sys_updated_on&gt;&lt;target&gt;macroponent&lt;/target&gt;&lt;type&gt;default&lt;/type&gt;&lt;/sys_ux_client_script&gt;&lt;/record_update&gt;</payload>
        <payload_hash>-1167391616</payload_hash>
        <record_name>Set category and orderType on select</record_name>
        <reverted_from/>
        <source>390c1d2e47c63110036bbce5536d43eb</source>
        <source_table>sys_update_set</source_table>
        <state>previous</state>
        <sys_created_by>admin</sys_created_by>
        <sys_created_on>2023-10-30 18:43:04</sys_created_on>
        <sys_id>b171c3c0471a3110036bbce5536d4373</sys_id>
        <sys_mod_count>0</sys_mod_count>
        <sys_recorded_at>18b81e586890000001</sys_recorded_at>
        <sys_updated_by>admin</sys_updated_by>
        <sys_updated_on>2023-10-30 18:43:04</sys_updated_on>
        <type>UX Client Script</type>
        <update_guid>3971c3c0941a311039a40bea6acf2972</update_guid>
        <update_guid_history>3971c3c0941a311039a40bea6acf2972:-1167391616,d17183c0c61a311030e0765702a6b0f8:-561679972</update_guid_history>
    </sys_update_version>
    <sys_metadata_delete action="INSERT_OR_UPDATE">
        <sys_audit_delete/>
        <sys_class_name>sys_metadata_delete</sys_class_name>
        <sys_created_by>admin</sys_created_by>
        <sys_created_on>2023-10-30 18:48:42</sys_created_on>
        <sys_db_object display_value="" name="sys_ux_client_script">sys_ux_client_script</sys_db_object>
        <sys_id>7f21d0ab66a5411caa032f59d0ef0a90</sys_id>
        <sys_metadata>d17183c0471a3110036bbce5536d43f7</sys_metadata>
        <sys_mod_count>0</sys_mod_count>
        <sys_name>Set category and orderType on select</sys_name>
        <sys_package display_value="AT&amp;amp;T Workspace" source="x_876519_att_work">e90c1d2e47c63110036bbce5536d43e6</sys_package>
        <sys_parent/>
        <sys_policy/>
        <sys_scope display_value="AT&amp;amp;T Workspace">e90c1d2e47c63110036bbce5536d43e6</sys_scope>
        <sys_scope_delete display_value="">03df7cc3232448a08c5efff9ca7f0610</sys_scope_delete>
        <sys_update_name>sys_ux_client_script_d17183c0471a3110036bbce5536d43f7</sys_update_name>
        <sys_update_version display_value="sys_ux_client_script_d17183c0471a3110036bbce5536d43f7">b171c3c0471a3110036bbce5536d4373</sys_update_version>
        <sys_updated_by>admin</sys_updated_by>
        <sys_updated_on>2023-10-30 18:48:42</sys_updated_on>
    </sys_metadata_delete>
</record_update>
